jupiter_nacos_client/__init__.py
jupiter_nacos_client/client.py
jupiter_nacos_client/service_invoker.py
jupiter_nacos_client-1.0.4.dist-info/licenses/LICENSE
jupiter_nacos_client-1.0.4.dist-info/METADATA
jupiter_nacos_client-1.0.4.dist-info/WHEEL
jupiter_nacos_client-1.0.4.dist-info/top_level.txt
jupiter_nacos_client-1.0.4.dist-info/RECORD
