Metadata-Version: 2.4
Name: jupiter-nacos-client
Version: 1.0.4
Summary: Simple nacos client package
Home-page: https://github.com/JupiterData-AI/jupiter-nacos-python
Author: tkiyer
Author-email: jiyidexin@yeah.net
License: Apache License
Platform: all
Requires-Python: >=3.7
License-File: LICENSE
Requires-Dist: requests
Requires-Dist: fastapi
Requires-Dist: uvicorn
Requires-Dist: nacos-sdk-python
Requires-Dist: python-dotenv
Requires-Dist: circuitbreaker
Requires-Dist: pydantic
Dynamic: author
Dynamic: author-email
Dynamic: description
Dynamic: description-content-type
Dynamic: home-page
Dynamic: license
Dynamic: license-file
Dynamic: platform
Dynamic: requires-dist
Dynamic: requires-python
Dynamic: summary
